redpipe/VERSION
redpipe/__init__.py
redpipe/connections.py
redpipe/exceptions.py
redpipe/fields.py
redpipe/futures.py
redpipe/keyspaces.py
redpipe/luascripts.py
redpipe/pipelines.py
redpipe/structs.py
redpipe/tasks.py
redpipe/version.py
redpipe-4.0.1.dist-info/LICENSE
redpipe-4.0.1.dist-info/METADATA
redpipe-4.0.1.dist-info/WHEEL
redpipe-4.0.1.dist-info/top_level.txt
redpipe-4.0.1.dist-info/RECORD
