Metadata-Version: 2.1
Name: redpipe
Version: 4.0.1
Summary: Easy Redis pipelines
Home-page: https://github.com/72squared/redpipe
Download-URL: https://github.com/72squared/redpipe/archive/4.0.1.tar.gz
Author: John Loehrer
Author-email: 72squared@gmail.com
License: MIT
Keywords: redis redis-pipeline orm database
Platform: UNKNOWN
Classifier: Development Status :: 5 - Production/Stable
Classifier: Programming Language :: Python
Classifier: Programming Language :: Python
Classifier: Programming Language :: Python :: Implementation :: CPython
Classifier: Programming Language :: Python :: Implementation :: PyPy
Classifier: Programming Language :: Python :: 3
Classifier: Programming Language :: Python :: 3.8
Classifier: Programming Language :: Python :: 3.9
Classifier: Environment :: Web Environment
Classifier: Operating System :: POSIX
License-File: LICENSE
Requires-Dist: redis (>=4.1.0)
